{
  "id": "starter-technology---computing-vol1",
  "title": "Technology & Computing Crossword Vol. 1",
  "theme": "Technology & Computing",
  "author": "Nightcrossing Engine",
  "date": "Starter Pack Vol. 1",
  "size": {
    "cols": 11,
    "rows": 9
  },
  "grid": [
    ".",
    ".",
    ".",
    ".",
    ".",
    ".",
    ".",
    "D",
    ".",
    ".",
    ".",
    "E",
    "D",
    "U",
    "C",
    "A",
    "T",
    "I",
    "O",
    "N",
    ".",
    ".",
    ".",
    ".",
    ".",
    ".",
    ".",
    ".",
    ".",
    "C",
    ".",
    ".",
    ".",
    ".",
    ".",
    ".",
    ".",
    "L",
    "I",
    "N",
    "K",
    ".",
    ".",
    "T",
    ".",
    "N",
    ".",
    ".",
    ".",
    ".",
    "R",
    ".",
    ".",
    ".",
    "E",
    "P",
    "O",
    "L",
    "Y",
    "T",
    "E",
    "C",
    "H",
    "N",
    "I",
    "C",
    ".",
    "D",
    ".",
    ".",
    ".",
    "D",
    ".",
    "A",
    ".",
    ".",
    "H",
    "T",
    "E",
    "C",
    "H",
    ".",
    "P",
    ".",
    "S",
    ".",
    ".",
    "S",
    ".",
    ".",
    ".",
    ".",
    ".",
    ".",
    ".",
    "H",
    ".",
    ".",
    "."
  ],
  "gridnums": [
    0,
    0,
    0,
    0,
    0,
    0,
    0,
    1,
    0,
    0,
    0,
    2,
    0,
    0,
    0,
    0,
    0,
    0,
    0,
    0,
    0,
    0,
    0,
    0,
    0,
    0,
    0,
    0,
    0,
    0,
    0,
    0,
    0,
    0,
    0,
    0,
    0,
    3,
    0,
    4,
    0,
    0,
    0,
    5,
    0,
    6,
    0,
    0,
    0,
    0,
    0,
    0,
    0,
    0,
    0,
    7,
    0,
    0,
    0,
    0,
    8,
    0,
    9,
    0,
    0,
    0,
    0,
    0,
    0,
    0,
    0,
    0,
    0,
    0,
    0,
    0,
    0,
    10,
    0,
    0,
    0,
    0,
    0,
    0,
    0,
    0,
    0,
    0,
    0,
    0,
    0,
    0,
    0,
    0,
    0,
    0,
    0,
    0,
    0
  ],
  "clues": {
    "across": [
      "2. Process of imparting knowledge, skill and judgment.",
      "3. Clickable connection to a URL",
      "7. Three-year post-secondary vocational training institute",
      "10. Technology."
    ],
    "down": [
      "1. Bar for app shortcuts",
      "4. Initialism of Nuclear Regulatory Commission.",
      "5. Technology.",
      "6. Connection point in a network",
      "8. Initialism of electronic data processing.",
      "9. Fixed-length output from input data"
    ]
  },
  "answers": {
    "across": [
      "EDUCATION",
      "LINK",
      "POLYTECHNIC",
      "TECH"
    ],
    "down": [
      "DOCK",
      "NRC",
      "TECHS",
      "NODE",
      "EDP",
      "HASH"
    ]
  }
}