{
  "id": "starter-history---civilization-vol2",
  "title": "History & Civilization Crossword Vol. 2",
  "theme": "History & Civilization",
  "author": "Nightcrossing Engine",
  "date": "Starter Pack Vol. 2",
  "size": {
    "cols": 7,
    "rows": 16
  },
  "grid": [
    ".",
    "O",
    "A",
    "T",
    "H",
    ".",
    ".",
    ".",
    ".",
    ".",
    "O",
    ".",
    ".",
    ".",
    ".",
    ".",
    ".",
    "M",
    ".",
    "P",
    ".",
    ".",
    ".",
    "R",
    "E",
    "L",
    "I",
    "C",
    ".",
    ".",
    ".",
    ".",
    ".",
    "K",
    ".",
    ".",
    ".",
    "L",
    "O",
    "R",
    "E",
    ".",
    ".",
    "R",
    ".",
    ".",
    "A",
    ".",
    "K",
    ".",
    "E",
    "M",
    "P",
    "I",
    "R",
    "E",
    ".",
    "I",
    ".",
    ".",
    "D",
    ".",
    "E",
    ".",
    "G",
    ".",
    ".",
    ".",
    ".",
    "P",
    ".",
    "N",
    "O",
    "B",
    "L",
    "E",
    ".",
    ".",
    ".",
    ".",
    "R",
    ".",
    ".",
    ".",
    "C",
    "O",
    "L",
    "O",
    "N",
    "Y",
    ".",
    ".",
    ".",
    ".",
    "N",
    ".",
    ".",
    ".",
    ".",
    ".",
    ".",
    "Z",
    ".",
    ".",
    ".",
    ".",
    "C",
    "R",
    "E",
    "S",
    "T",
    "."
  ],
  "gridnums": [
    0,
    1,
    0,
    2,
    0,
    0,
    0,
    0,
    0,
    0,
    0,
    0,
    0,
    0,
    0,
    0,
    0,
    0,
    0,
    3,
    0,
    0,
    0,
    4,
    0,
    0,
    0,
    0,
    0,
    0,
    0,
    0,
    0,
    0,
    0,
    0,
    0,
    5,
    0,
    6,
    0,
    0,
    0,
    7,
    0,
    0,
    0,
    0,
    8,
    0,
    9,
    0,
    0,
    0,
    0,
    0,
    0,
    0,
    0,
    0,
    0,
    0,
    0,
    0,
    0,
    0,
    0,
    0,
    0,
    0,
    0,
    10,
    0,
    11,
    0,
    0,
    0,
    0,
    0,
    0,
    0,
    0,
    0,
    0,
    12,
    0,
    0,
    0,
    0,
    0,
    0,
    0,
    0,
    0,
    0,
    0,
    0,
    0,
    0,
    0,
    0,
    0,
    0,
    0,
    0,
    0,
    13,
    0,
    0,
    0,
    0,
    0
  ],
  "clues": {
    "across": [
      "9. Group of nations under one ruler",
      "1. Solemn promise",
      "4. Surviving object from the past",
      "5. Traditional knowledge passed down",
      "10. Person of high social rank",
      "12. Settlement in a new territory",
      "13. Heraldic emblem of a family"
    ],
    "down": [
      "3. Long infantry weapon with a point",
      "undefined. Protective armor carried in battle",
      "undefined. Medieval trade organization",
      "2. Large scholarly book",
      "6. Surprise military attack",
      "7. Period of a monarch's rule",
      "8. Strong central tower of a castle",
      "11. Metal alloy that named an age",
      "undefined. Ancient rolled-up document",
      "undefined. Formal agreement between nations",
      "undefined. Governing council in ancient Rome"
    ]
  },
  "answers": {
    "across": [
      "EMPIRE",
      "OATH",
      "RELIC",
      "LORE",
      "NOBLE",
      "COLONY",
      "CREST"
    ],
    "down": [
      "PIKE",
      "SHIELD",
      "GUILD",
      "TOME",
      "RAID",
      "REIGN",
      "KEEP",
      "BRONZE",
      "SCROLL",
      "TREATY",
      "SENATE"
    ]
  }
}