{
  "id": "starter-technology---computing-vol1",
  "title": "Technology & Computing 1",
  "theme": "Technology & Computing",
  "author": "Nightcrossing Engine",
  "date": "Starter Pack Vol. 1",
  "size": {
    "cols": 11,
    "rows": 10
  },
  "grid": [
    ".",
    ".",
    ".",
    ".",
    ".",
    ".",
    ".",
    ".",
    ".",
    "D",
    ".",
    ".",
    ".",
    ".",
    ".",
    ".",
    ".",
    "P",
    "I",
    "X",
    "E",
    "L",
    ".",
    ".",
    ".",
    ".",
    ".",
    ".",
    ".",
    ".",
    ".",
    "B",
    ".",
    ".",
    "M",
    ".",
    ".",
    ".",
    ".",
    ".",
    ".",
    ".",
    "U",
    ".",
    "B",
    "O",
    "O",
    "T",
    ".",
    ".",
    "P",
    "I",
    "N",
    "G",
    ".",
    ".",
    "D",
    ".",
    "E",
    ".",
    "A",
    ".",
    "C",
    ".",
    ".",
    ".",
    ".",
    "A",
    ".",
    "C",
    "U",
    "R",
    "S",
    "O",
    "R",
    ".",
    ".",
    ".",
    "L",
    ".",
    "H",
    ".",
    "R",
    ".",
    "N",
    ".",
    ".",
    ".",
    ".",
    ".",
    ".",
    ".",
    ".",
    "A",
    ".",
    ".",
    ".",
    ".",
    ".",
    ".",
    ".",
    ".",
    ".",
    "S",
    "Y",
    "N",
    "C",
    ".",
    ".",
    "."
  ],
  "gridnums": [
    0,
    0,
    0,
    0,
    0,
    0,
    0,
    0,
    0,
    1,
    0,
    0,
    0,
    0,
    0,
    0,
    0,
    2,
    0,
    0,
    0,
    0,
    0,
    0,
    0,
    0,
    0,
    0,
    0,
    0,
    0,
    0,
    0,
    0,
    3,
    0,
    0,
    0,
    0,
    0,
    0,
    0,
    0,
    0,
    4,
    0,
    0,
    5,
    0,
    0,
    6,
    7,
    0,
    0,
    0,
    0,
    0,
    0,
    0,
    0,
    8,
    0,
    0,
    0,
    0,
    0,
    0,
    0,
    0,
    9,
    0,
    0,
    0,
    0,
    0,
    0,
    0,
    0,
    0,
    0,
    0,
    0,
    0,
    0,
    0,
    0,
    0,
    0,
    0,
    0,
    0,
    0,
    0,
    0,
    0,
    0,
    0,
    0,
    0,
    0,
    0,
    0,
    0,
    10,
    0,
    0,
    0,
    0,
    0,
    0
  ],
  "clues": {
    "across": [
      "2. Smallest unit of a digital image",
      "4. Start up a computer",
      "6. Test network connectivity",
      "9. On-screen pointer",
      "10. Match data across devices"
    ],
    "down": [
      "1. Find and fix errors in code",
      "3. Pop-up dialog window",
      "5. Technology.",
      "7. Small graphical image representing an app",
      "8. Ordered collection of elements"
    ]
  },
  "answers": {
    "across": [
      "PIXEL",
      "BOOT",
      "PING",
      "CURSOR",
      "SYNC"
    ],
    "down": [
      "DEBUG",
      "MODAL",
      "TECH",
      "ICON",
      "ARRAY"
    ]
  },
  "hints": {
    "down-1": "Action, or a session, of reviewing source code to find and eliminate errors.",
    "across-2": "Unit of measure used in screen displays, resolutions, and similar visual media that represents either linear measure or area.",
    "down-3": "Of, relating to, or describing the mood of a clause.",
    "across-4": "A kind of sports shoe worn by players of certain games such as cricket and football.",
    "down-5": "Denotes technology businesses or the technology industry, especially in the field of computing and the Internet.",
    "across-6": "Latency.",
    "down-7": "An image used to represent a user; an avatar or profile picture.",
    "down-8": "Orderly series, arrangement or sequence.",
    "across-9": "An indicator, often a blinking line or bar, indicating where the next insertion or other edit will take place.",
    "across-10": "To flush all pending I/O operations to disk."
  }
}